RobotframeworkYetAnotherOcrLibrary/__init__.py
RobotframeworkYetAnotherOcrLibrary/version.py
RobotframeworkYetAnotherOcrLibrary/exception/__init__.py
RobotframeworkYetAnotherOcrLibrary/exception/ocr_error.py
RobotframeworkYetAnotherOcrLibrary/keywords/__init__.py
RobotframeworkYetAnotherOcrLibrary/keywords/detection.py
RobotframeworkYetAnotherOcrLibrary/keywords/visualizer.py
RobotframeworkYetAnotherOcrLibrary/model/__init__.py
RobotframeworkYetAnotherOcrLibrary/model/object_detection.py
RobotframeworkYetAnotherOcrLibrary/opencv/__init__.py
RobotframeworkYetAnotherOcrLibrary/opencv/algorithm.py
RobotframeworkYetAnotherOcrLibrary/opencv/template_matching.py
RobotframeworkYetAnotherOcrLibrary/robotframework/__init__.py
RobotframeworkYetAnotherOcrLibrary/robotframework/robotlog.py
RobotframeworkYetAnotherOcrLibrary/util/__init__.py
RobotframeworkYetAnotherOcrLibrary/util/data_type.py
robotframework_yet_another_ocr_library-0.0.9.dist-info/LICENSE
robotframework_yet_another_ocr_library-0.0.9.dist-info/METADATA
robotframework_yet_another_ocr_library-0.0.9.dist-info/WHEEL
robotframework_yet_another_ocr_library-0.0.9.dist-info/top_level.txt
robotframework_yet_another_ocr_library-0.0.9.dist-info/RECORD
